promptedgraphs/__init__.py
promptedgraphs/__main__.py
promptedgraphs/cli.py
promptedgraphs/code_execution/__init__.py
promptedgraphs/code_execution/safer_python_exec.py
promptedgraphs/config.py
promptedgraphs/data_extraction.py
promptedgraphs/data_modeling/__init__.py
promptedgraphs/data_modeling/conceptual.py
promptedgraphs/data_modeling/logical.py
promptedgraphs/data_modeling/physical.py
promptedgraphs/entity_linking/README.md
promptedgraphs/entity_linking/__init__.py
promptedgraphs/entity_linking/link.py
promptedgraphs/entity_linking/upsertion.py
promptedgraphs/entity_recognition.py
promptedgraphs/entity_resolution/__init__.py
promptedgraphs/entity_resolution/resolve.py
promptedgraphs/extraction/__init__.py
promptedgraphs/extraction/data_from_text.py
promptedgraphs/extraction/entities_from_text.py
promptedgraphs/generation/__init__.py
promptedgraphs/generation/data_from_model.py
promptedgraphs/generation/schema_from_data.py
promptedgraphs/generation/schema_from_model.py
promptedgraphs/helpers.py
promptedgraphs/llms/__init__.py
promptedgraphs/llms/anthropic_chat.py
promptedgraphs/llms/chat.py
promptedgraphs/llms/coding.py
promptedgraphs/llms/helpers.py
promptedgraphs/llms/openai_chat.py
promptedgraphs/llms/openai_streaming.py
promptedgraphs/llms/usage.py
promptedgraphs/models.py
promptedgraphs/normalization/__init__.py
promptedgraphs/normalization/object_to_data.py
promptedgraphs/normalization/schema_to_schema.py
promptedgraphs/normalization/vis_graphs.py
promptedgraphs/parsers.py
promptedgraphs/sources/__init__.py
promptedgraphs/sources/datagraph_from_class.py
promptedgraphs/sources/datagraph_from_pydantic.py
promptedgraphs/statistical/__init__.py
promptedgraphs/statistical/data_analysis.py
promptedgraphs/utils/__init__.py
promptedgraphs/validation/__init__.py
promptedgraphs/validation/validate_data.py
promptedgraphs/validation/validate_schema.py
promptedgraphs/vis.py
promptedgraphs-0.4.3.dist-info/LICENSE
promptedgraphs-0.4.3.dist-info/METADATA
promptedgraphs-0.4.3.dist-info/WHEEL
promptedgraphs-0.4.3.dist-info/entry_points.txt
promptedgraphs-0.4.3.dist-info/RECORD
