Metadata-Version: 2.1
Name: promptedgraphs
Version: 0.4.3
Summary: From Dataset Labeling to Deployment: The Power of NLP and LLMs Combined.
License: MIT
Author: Sean Kruzel
Author-email: sean@closedloop.tech
Requires-Python: >=3.10,<4.0
Classifier: License :: OSI Approved :: MIT License
Classifier: Operating System :: OS Independent
Classifier: Programming Language :: Python :: 3
Classifier: Programming Language :: Python :: 3.10
Classifier: Programming Language :: Python :: 3.11
Classifier: Programming Language :: Python :: 3.12
Classifier: Topic :: Software Development :: Libraries :: Python Modules
Requires-Dist: amrlib (>=0.8.0,<0.9.0)
Requires-Dist: beautifulsoup4 (>=4.12.3,<5.0.0)
Requires-Dist: cohere (>=4.47,<5.0)
Requires-Dist: colorama (>=0.4.6,<0.5.0)
Requires-Dist: datamodel-code-generator (>=0.25.5,<0.26.0)
Requires-Dist: flair (>=0.13.1,<0.14.0)
Requires-Dist: gcloud (>=0.18.3,<0.19.0)
Requires-Dist: googlemaps (>=4.10.0,<5.0.0)
Requires-Dist: httpx (>=0.27.0,<0.28.0)
Requires-Dist: ipykernel (>=6.29.2,<7.0.0)
Requires-Dist: jsonpath-ng (>=1.6.1,<2.0.0)
Requires-Dist: jupyter (>=1.0.0,<2.0.0)
Requires-Dist: matplotlib (>=3.8.0,<4.0.0)
Requires-Dist: networkx (>=3.2.1,<4.0.0)
Requires-Dist: nltk (>=3.8.1,<4.0.0)
Requires-Dist: openai (>=1.12.0,<2.0.0)
Requires-Dist: pandas (>=2.2.1,<3.0.0)
Requires-Dist: penman (>=1.3.0,<2.0.0)
Requires-Dist: pre-commit (>=3.3.1,<4.0.0)
Requires-Dist: pyarrow (>=15.0.2,<16.0.0)
Requires-Dist: pydantic (>=2.6.3,<3.0.0)
Requires-Dist: pydot (>=2.0.0,<3.0.0)
Requires-Dist: pyfiglet (>=1.0.2,<2.0.0)
Requires-Dist: scikit-learn (>=1.4.0,<2.0.0)
Requires-Dist: seaborn (>=0.13.2,<0.14.0)
Requires-Dist: spacy (>=3.7.4,<4.0.0)
Requires-Dist: spacy-experimental (>=0.6.4,<0.7.0)
Requires-Dist: tabulate (>=0.9.0,<0.10.0)
Requires-Dist: termcolor (>=2.4.0,<3.0.0)
Requires-Dist: tiktoken (>=0.6.0,<0.7.0)
Requires-Dist: torch (>=2.2.2,<3.0.0)
Requires-Dist: transformers (>=4.37.2,<5.0.0)
Requires-Dist: twine (>=5.0.0,<6.0.0)
Requires-Dist: typer (>=0.9.0,<0.10.0)
Requires-Dist: unidecode (>=1.3.8,<2.0.0)
Project-URL: Bug Tracker, https://github.com/closedLoop-technologies/promptedgraphs/issues
Project-URL: Repository, https://github.com/closedLoop-technologies/promptedgraphs
